etomo/__init__.py
etomo/info.py
etomo/operators/__init__.py
etomo/operators/fourier/__init__.py
etomo/operators/fourier/fourier.py
etomo/operators/fourier/utils.py
etomo/operators/gradient/__init__.py
etomo/operators/gradient/gradient.py
etomo/operators/linear/HOTV.py
etomo/operators/linear/__init__.py
etomo/operators/linear/base.py
etomo/operators/linear/utils.py
etomo/operators/linear/wavelet.py
etomo/operators/radon/__init__.py
etomo/operators/radon/radon.py
etomo/operators/utils/__init__.py
etomo/optimizers/__init__.py
etomo/optimizers/forward_backward.py
etomo/optimizers/primal_dual.py
etomo/optimizers/utils/__init__.py
etomo/optimizers/utils/cost.py
etomo/optimizers/utils/reweight.py
etomo/reconstructors/__init__.py
etomo/reconstructors/base.py
etomo/reconstructors/forwardtomo.py
pysap_etomo-0.0.1.dist-info/LICENSE
pysap_etomo-0.0.1.dist-info/METADATA
pysap_etomo-0.0.1.dist-info/WHEEL
pysap_etomo-0.0.1.dist-info/top_level.txt
pysap_etomo-0.0.1.dist-info/RECORD
