Metadata-Version: 2.1
Name: pysap-etomo
Version: 0.0.1
Summary: Python Sparse data Analysis Package external ETOMO plugin.
Home-page: https://github.com/CEA-COSMIC/pysap-etomo
Author: 
Requires-Dist: scikit-learn (>=0.19.1)
Requires-Dist: progressbar2 (>=3.34.3)
Requires-Dist: joblib
Requires-Dist: scipy (>=1.3.0)
Requires-Dist: scikit-image
